simplesm/__init__.py
simplesm/example.py
simplesm/simplesm.py
simplesm-0.1.4.dist-info/LICENSE
simplesm-0.1.4.dist-info/METADATA
simplesm-0.1.4.dist-info/WHEEL
simplesm-0.1.4.dist-info/top_level.txt
simplesm-0.1.4.dist-info/RECORD
